Workbook

Sheet README
A1: Halden Energy — Quarter 4: What Baton Rouge pays for Texas crude
A3: Decision: set the internal transfer price for Permian crude sold to the Baton Rouge refinery.
A4: Three anchor options: market-based, marginal-cost, or a lazy midpoint. You may also set an intermediate value.
A7: How this workbook is organized:
A8: Tab: Data — Permian | B8: The lifting costs and cost constants you compute from. Read-only reference.
A9: Tab: Data — Compensation | B9: The segment compensation plan. Read this carefully — it explains the politics.
A10: Tab: Worked Example | B10: A fully solved example on a PRIOR period (WTI $68). Study the method here first.
A11: Tab: Your Analysis | B11: This quarter (WTI $74). Fill the YELLOW cells. This is your work.
A13: Color legend:
A14: Blue text | B14: A hardcoded input or given constant. Do not change.
A15: Black text | B15: A formula that computes from other cells.
A16: Yellow fill | B16: A cell for YOU to fill in on the Your Analysis tab.
A18: The key insight to test:
A19: Halden's integrated margin per barrel does NOT change with the transfer price.
A20: The transfer price only splits that fixed margin between Upstream and Refining.
A21: Check this yourself in the Worked Example before doing Your Analysis.

Sheet Data — Permian
A1: Permian Lifting Costs by Vintage
A3: Vintage | B3: Cash lifting cost ($/bbl) | C3: Production share
A4: 2021 | B4: 11.5 | C4: 0.18
A5: 2022 | B5: 10.2 | C5: 0.24
A6: 2023 | B6: 9.4 | C6: 0.31
A7: 2024 | B7: 8.8 | C7: 0.27
A9: Cost constants ($/bbl):
A10: WTI benchmark (this quarter) | B10: 74
A11: Permian wellhead discount to WTI | B11: 3.5
A12: Gathering cost | B12: 2.1
A13: Transport Permian to Baton Rouge | B13: 3.2
A14: Short-run capital recovery charge | B14: 4.6
A15: Gulf Coast 3-2-1 crack (this quarter) | B15: 21.5
A16: Baton Rouge complexity premium | B16: 4.75
A17: Baton Rouge refining opex | B17: 5.9
A18: Geneva arbitrage capture rate | B18: 0.35
A19: Geneva max arbitrage volume (bbl/day) | B19: 40000

Sheet Data — Compensation
A1: Segment Compensation Plan
A2: Segment heads are bonused on their own segment margin vs target. Nobody rewrote this when the EVP role was created.
A4: Segment | B4: Bonus basis | C4: Target margin ($/bbl)
A5: upstream | B5: segment margin per bbl vs target | C5: 45
A6: refining | B6: segment margin per bbl vs target | C6: 30
A7: trading | B7: desk P&L vs budget | C7: —

Sheet Worked Example
A1: Worked Example — Prior Period (WTI $68). Study the method, then replicate on Your Analysis.
A2: All figures $/bbl. Blue = given input. Black = formula. The point: integrated margin is the same under every transfer price.
A4: Inputs
A5: WTI (prior) | B5: 68
A6: Permian wellhead discount | B6: 3.5
A7: Transport to Baton Rouge | B7: 3.2
A8: Delivered marginal cost | B8: 14.1
A9: Short-run capital charge | B9: 4.6
A10: Gulf Coast crack (prior) | B10: 19
A11: BR complexity premium | B11: 4.75
A12: BR opex | B12: 5.9
A14: Derived quantities
A15: Permian realized wellhead (WTI - discount) | B15: =B5-B6
A16: Product slate value (realized + crack + complexity) | B16: =B15+B10+B11
A17: INTEGRATED margin (product value - marginal cost - BR opex) | B17: =B16-B8-B12
A19: Transfer price options
A20: Market-based TP (realized + transport) | B20: =B15+B7
A21: Marginal-cost TP (marginal cost + capital charge) | B21: =B8+B9
A23: Segment split check (shows integrated margin is invariant)
A24: Transfer price | B24: Upstream margin | C24: Refining margin | D24: Sum (= integrated)
A25: =B20 | B25: =A25-B8 | C25: =B16-A25-B12 | D25: =B25+C25
A26: =B21 | B26: =A26-B8 | C26: =B16-A26-B12 | D26: =B26+C26
A28: Note: column 4 (the sum) equals the integrated margin above under BOTH transfer prices.
A29: The transfer price moved margin between Upstream and Refining. It did not change the total.

Sheet Your Analysis
A1: Your Analysis — This quarter (WTI $74). Fill the YELLOW cells using the same method as the Worked Example.
A2: Inputs are pulled from the Data — Permian tab (blue). Compute the yellow cells with formulas.
A4: Inputs (from Data — Permian)
A5: WTI | B5: ='Data — Permian'!B10
A6: Permian wellhead discount | B6: ='Data — Permian'!B11
A7: Transport to Baton Rouge | B7: ='Data — Permian'!B13
A8: Delivered marginal cost (=lift 8.80 + gathering + transport) | B8: =8.8+'Data — Permian'!B12+'Data — Permian'!B13
A9: Short-run capital charge | B9: ='Data — Permian'!B14
A10: Gulf Coast crack | B10: ='Data — Permian'!B15
A11: BR complexity premium | B11: ='Data — Permian'!B16
A12: BR opex | B12: ='Data — Permian'!B17
A14: Your computations — fill the yellow cells
A15: Permian realized wellhead (WTI - discount)
A16: Product slate value (realized + crack + complexity)
A17: INTEGRATED margin (product value - marginal cost - BR opex)
A18: Market-based transfer price (realized + transport)
A19: Marginal-cost transfer price (marginal cost + capital charge)
A20: Lazy midpoint transfer price (average of the two above)
A22: Segment split & bonus impact — fill the yellow cells
A23: Transfer price | B23: Upstream margin | C23: Refining margin | D23: Upstream vs target | E23: Refining vs target
A24: Market
A25: Marginal cost
A26: Lazy midpoint
A28: Targets: Upstream $45.00/bbl, Refining $30.00/bbl (from Data — Compensation).
A29: Geneva arbitrage under lazy midpoint — fill the yellow cell:
A30: Value captured by Geneva ($/bbl on the gap) = 0.35 x (market TP - lazy TP)
